httpunixsocketconnection/__init__.py
httpunixsocketconnection/py.typed
httpunixsocketconnection-1.0.1.dist-info/LICENSE
httpunixsocketconnection-1.0.1.dist-info/WHEEL
httpunixsocketconnection-1.0.1.dist-info/METADATA
httpunixsocketconnection-1.0.1.dist-info/RECORD
