Metadata-Version: 2.1
Name: httpunixsocketconnection
Version: 1.0.1
Summary: Really small Python class that extends native http.client.HTTPConnection allowing sending HTTP requests to Unix Sockets
Home-page: https://github.com/marverix/HTTPUnixSocketConnection
License: Apache-2.0
Keywords: http,unix,sockets,socket,requests,connection
Author: Marek Sierociński
Author-email: mareksierocinski@gmail.com
Requires-Python: >=3.8,<4.0
Classifier: License :: OSI Approved :: Apache Software License
Classifier: Operating System :: Unix
Classifier: Programming Language :: Python :: 3
Classifier: Programming Language :: Python :: 3.10
Classifier: Programming Language :: Python :: 3.8
Classifier: Programming Language :: Python :: 3.9
Classifier: Topic :: Software Development :: Libraries
Classifier: Topic :: Software Development :: Libraries :: Python Modules
Project-URL: Repository, https://github.com/marverix/HTTPUnixSocketConnection
